insta_rag/__init__.py
insta_rag/chunking/__init__.py
insta_rag/chunking/base.py
insta_rag/chunking/semantic.py
insta_rag/chunking/utils.py
insta_rag/core/__init__.py
insta_rag/core/client.py
insta_rag/core/config.py
insta_rag/core/retrieval_method.py
insta_rag/embedding/__init__.py
insta_rag/embedding/base.py
insta_rag/embedding/openai.py
insta_rag/models/__init__.py
insta_rag/models/chunk.py
insta_rag/models/document.py
insta_rag/models/response.py
insta_rag/retrieval/__init__.py
insta_rag/retrieval/base.py
insta_rag/retrieval/keyword_search.py
insta_rag/retrieval/query_generator.py
insta_rag/retrieval/reranker.py
insta_rag/retrieval/vector_search.py
insta_rag/utils/exceptions.py
insta_rag/utils/pdf_processing.py
insta_rag/vectordb/__init__.py
insta_rag/vectordb/base.py
insta_rag/vectordb/qdrant.py
insta_rag-0.2.0.dist-info/WHEEL
insta_rag-0.2.0.dist-info/METADATA
insta_rag-0.2.0.dist-info/RECORD
