Metadata-Version: 2.4
Name: insta-rag
Version: 0.2.0
Summary: A RAG (Retrieval-Augmented Generation) library for document processing and retrieval.
Keywords: rag,retrieval-augmented-generation,llm,ai,nlp
Author: Aukik Aurnab, Tahmidul Islam, MD Ikramul Kayes
Author-email: Aukik Aurnab <aukikaurnabx@gmail.com>, Tahmidul Islam <me@tahmidul612.com>, MD Ikramul Kayes <ikramul.kayesgg@gmail.com>
License-Expression: MIT
Classifier: Development Status :: 4 - Beta
Classifier: Intended Audience :: Developers
Classifier: Intended Audience :: Science/Research
Classifier: Operating System :: OS Independent
Classifier: Programming Language :: Python :: 3.9
Classifier: Programming Language :: Python :: 3.10
Classifier: Programming Language :: Python :: 3.11
Classifier: Programming Language :: Python :: 3.12
Classifier: Programming Language :: Python :: 3.13
Classifier: Topic :: Scientific/Engineering :: Artificial Intelligence
Classifier: Topic :: Scientific/Engineering :: Information Analysis
Classifier: Topic :: Text Processing :: Indexing
Classifier: Topic :: Software Development :: Libraries :: Python Modules
Classifier: Natural Language :: English
Requires-Dist: openai>=1.12.0
Requires-Dist: qdrant-client>=1.7.0
Requires-Dist: pdfplumber>=0.10.3
Requires-Dist: pypdf2>=3.0.1
Requires-Dist: tiktoken>=0.5.2
Requires-Dist: numpy>=1.24.0
Requires-Dist: python-dotenv>=1.0.0
Requires-Dist: cohere>=4.47.0
Requires-Dist: pydantic>=2.5.0
Requires-Dist: requests>=2.32.5
Requires-Dist: rank-bm25>=0.2.2
Requires-Python: >=3.9
Project-URL: Bug Tracker, https://github.com/AI-Buddy-Catalyst-Labs/insta_rag/issues
Project-URL: Documentation, https://github.com/AI-Buddy-Catalyst-Labs/insta_rag/wiki
Project-URL: Homepage, https://github.com/AI-Buddy-Catalyst-Labs/insta_rag
